odoo/addons/account_payment_unece/README.rst
odoo/addons/account_payment_unece/__init__.py
odoo/addons/account_payment_unece/__manifest__.py
odoo/addons/account_payment_unece/data/account_payment_method.xml
odoo/addons/account_payment_unece/data/unece.xml
odoo/addons/account_payment_unece/i18n/account_payment_unece.pot
odoo/addons/account_payment_unece/models/__init__.py
odoo/addons/account_payment_unece/models/account_payment_method.py
odoo/addons/account_payment_unece/models/unece_code_list.py
odoo/addons/account_payment_unece/static/description/icon.png
odoo/addons/account_payment_unece/tests/__init__.py
odoo/addons/account_payment_unece/tests/test_account_invoice.py
odoo/addons/account_payment_unece/views/account_payment_method.xml
odoo11_addon_account_payment_unece-11.0.1.0.1.dist-info/METADATA
odoo11_addon_account_payment_unece-11.0.1.0.1.dist-info/WHEEL
odoo11_addon_account_payment_unece-11.0.1.0.1.dist-info/top_level.txt
odoo11_addon_account_payment_unece-11.0.1.0.1.dist-info/RECORD
